Workbook
Name Slicer_Department: #N/A
Name Slicer_Location: #N/A

Sheet Financial Variance Detection Mo
A3: Row Labels | B3: Sum of Revenue_per_Hr | C3: Sum of Maintenance_Cost | D3: Sum of Maintenance_Variance
A4: Charitable Gaming | B4: 46496.83 | C4: 53360.423 | D4: -50250.088
A5: Entertainment | B5: 6328.3794 | C5: 7339.6148 | D5: -6719.2296
A6: F&B / Kitchen | B6: 5971.6662 | C6: 7131.0186 | D6: -6677.7334
A7: Gaming - Bingo | B7: 48947.415 | C7: 55904.084 | D7: -56295.522
A8: Gaming - Electronic | B8: 202869.21 | C8: 233061.43 | D8: -225776.68
A9: Guest & Security | B9: 16609.835 | C9: 19289.499 | D9: -14686.818
A10: Grand Total | B10: 327223.33 | C10: 376086.07 | D10: -360406.07

Sheet Rama_Truth1
A1: Date | B1: Department | C1: Asset_ID | D1: Location | E1: Game_type | F1: Unit_Cost | G1: Revenue_per_Hr | H1: Raw_revenu_per_Hr | I1: Maintenance_Cost | J1: Raw_maintenance_Cost_MTBF | K1: RPSF_Utilization | L1: Risk_Score(1-10) | M1: Recommended_Action | N1: Game_Name | O1: Manifacturer | P1: Maintenance_Benchmark | Q1: Maintenance_Variance | R1: Risk_Category
A2: =DATE(2026,1,1)+INT((ROW()-2)/70) -> 46023 | B2: Gaming - Electronic | C2: EGM-SL-001 | D2: NORTH_ZONE | E2: SLOT_PROGRESSIVE | F2: 1.26 | G2: =ABS(Table2[[#This Row],[Raw_revenu_per_Hr]]) -> 95 | H2: 95 | I2: =ABS(Table2[[#This Row],[Raw_maintenance_Cost_MTBF]]) -> 120 | J2: 120 | K2: 0.91 | L2: =MAX(1,MIN(10,ROUND(10-(K2*10),0))) -> 1 | M2: Monitor | N2: Wheel of Fortune | O2: IGT | P2: =_xlfn.XLOOKUP(C2, Financial_Variance!B:B, Financial_Variance!H:H, 0) -> 100 | Q2: =P17-I6 -> -20 | R2: =IF(L2<=2,"Low",IF(L2<=4,"Medium",IF(L2<=7,"High","Critical"))) -> Low
A3: =DATE(2026,1,1)+INT((ROW()-2)/70) -> 46023 | B3: Gaming - Electronic | C3: EGM-SL-002 | D3: NORTH_ZONE | E3: SLOT_PROGRESSIVE | F3: 1.26 | G3: =ABS(Table2[[#This Row],[Raw_revenu_per_Hr]]) -> 95 | H3: 95 | I3: =ABS(Table2[[#This Row],[Raw_maintenance_Cost_MTBF]]) -> 120 | J3: 120 | K3: 0.91 | L3: =MAX(1,MIN(10,ROUND(10-(K3*10),0))) -> 1 | M3: Monitor | N3: Cash Eruption | O3: IGT | P3: =_xlfn.XLOOKUP(C3, Financial_Variance!B:B, Financial_Variance!H:H, 0) -> 100 | Q3: =P18-I7 -> -20 | R3: =IF(L3<=2,"Low",IF(L3<=4,"Medium",IF(L3<=7,"High","Critical"))) -> Low
A4: =DATE(2026,1,1)+INT((ROW()-2)/70) -> 46023 | B4: Gaming - Electronic | C4: EGM-SL-003 | D4: NORTH_ZONE | E4: SLOT_PROGRESSIVE | F4: 1.26 | G4: =ABS(Table2[[#This Row],[Raw_revenu_per_Hr]]) -> 95 | H4: 95 | I4: =ABS(Table2[[#This Row],[Raw_maintenance_Cost_MTBF]]) -> 120 | J4: 120 | K4: 0.91 | L4: =MAX(1,MIN(10,ROUND(10-(K4*10),0))) -> 1 | M4: Monitor | N4: Dancing Drums | O4: SG | P4: =_xlfn.XLOOKUP(C4, Financial_Variance!B:B, Financial_Variance!H:H, 0) -> 100 | Q4: =P19-I8 -> -20 | R4: =IF(L4<=2,"Low",IF(L4<=4,"Medium",IF(L4<=7,"High","Critical"))) -> Low
A5: =DATE(2026,1,1)+INT((ROW()-2)/70) -> 46023 | B5: Gaming - Electronic | C5: EGM-SL-004 | D5: NORTH_ZONE | E5: SLOT_PROGRESSIVE | F5: 1.26 | G5: =ABS(Table2[[#This Row],[Raw_revenu_per_Hr]]) -> 95 | H5: 95 | I5: =ABS(Table2[[#This Row],[Raw_maintenance_Cost_MTBF]]) -> 120 | J5: 120 | K5: 0.91 | L5: =MAX(1,MIN(10,ROUND(10-(K5*10),0))) -> 1 | M5: Monitor | N5: Coin Combo Mouse | O5: AGS | P5: =_xlfn.XLOOKUP(C5, Financial_Variance!B:B, Financial_Variance!H:H, 0) -> 100 | Q5: =P20-I9 -> -20 | R5: =IF(L5<=2,"Low",IF(L5<=4,"Medium",IF(L5<=7,"High","Critical"))) -> Low
A6: =DATE(2026,1,1)+INT((ROW()-2)/70) -> 46023 | B6: Gaming - Electronic | C6: EGM-SL-005 | D6: NORTH_ZONE | E6: SLOT_PROGRESSIVE | F6: 1.26 | G6: =ABS(Table2[[#This Row],[Raw_revenu_per_Hr]]) -> 95 | H6: 95 | I6: =ABS(Table2[[#This Row],[Raw_maintenance_Cost_MTBF]]) -> 120 | J6: 120 | K6: 0.91 | L6: =MAX(1,MIN(10,ROUND(10-(K6*10),0))) -> 1 | M6: Monitor | N6: Coin Combo Cow | O6: AGS | P6: =_xlfn.XLOOKUP(C6, Financial_Variance!B:B, Financial_Variance!H:H, 0) -> 100 | Q6: =P21-I10 -> -20 | R6: =IF(L6<=2,"Low",IF(L6<=4,"Medium",IF(L6<=7,"High","Critical"))) -> Low
A7: =DATE(2026,1,1)+INT((ROW()-2)/70) -> 46023 | B7: Gaming - Electronic | C7: EGM-SL-006 | D7: NORTH_ZONE | E7: SLOT_PROGRESSIVE | F7: 1.26 | G7: =ABS(Table2[[#This Row],[Raw_revenu_per_Hr]]) -> 95 | H7: 95 | I7: =ABS(Table2[[#This Row],[Raw_maintenance_Cost_MTBF]]) -> 120 | J7: 120 | K7: 0.91 | L7: =MAX(1,MIN(10,ROUND(10-(K7*10),0))) -> 1 | M7: Monitor | N7: Ultra Hot | O7: IGT | P7: =_xlfn.XLOOKUP(C7, Financial_Variance!B:B, Financial_Variance!H:H, 0) -> 100 | Q7: =P22-I11 -> -20 | R7: =IF(L7<=2,"Low",IF(L7<=4,"Medium",IF(L7<=7,"High","Critical"))) -> Low
A8: =DATE(2026,1,1)+INT((ROW()-2)/70) -> 46023 | B8: Gaming - Electronic | C8: EGM-SL-007 | D8: NORTH_ZONE | E8: SLOT_PROGRESSIVE | F8: 1.26 | G8: =ABS(Table2[[#This Row],[Raw_revenu_per_Hr]]) -> 95 | H8: 95 | I8: =ABS(Table2[[#This Row],[Raw_maintenance_Cost_MTBF]]) -> 120 | J8: 120 | K8: 0.91 | L8: =MAX(1,MIN(10,ROUND(10-(K8*10),0))) -> 1 | M8: Monitor | N8: Drop Lock | O8: Bally | P8: =_xlfn.XLOOKUP(C8, Financial_Variance!B:B, Financial_Variance!H:H, 0) -> 100 | Q8: =P23-I12 -> -35 | R8: =IF(L8<=2,"Low",IF(L8<=4,"Medium",IF(L8<=7,"High","Critical"))) -> Low
A9: =DATE(2026,1,1)+INT((ROW()-2)/70) -> 46023 | B9: Gaming - Electronic | C9: EGM-SL-008 | D9: NORTH_ZONE | E9: SLOT_PROGRESSIVE | F9: 1.26 | G9: =ABS(Table2[[#This Row],[Raw_revenu_per_Hr]]) -> 95 | H9: 95 | I9: =ABS(Table2[[#This Row],[Raw_maintenance_Cost_MTBF]]) -> 120 | J9: 120 | K9: 0.91 | L9: =MAX(1,MIN(10,ROUND(10-(K9*10),0))) -> 1 | M9: Monitor | N9: Hot Hit | O9: Bally | P9: =_xlfn.XLOOKUP(C9, Financial_Variance!B:B, Financial_Variance!H:H, 0) -> 100 | Q9: =P24-I13 -> -35 | R9: =IF(L9<=2,"Low",IF(L9<=4,"Medium",IF(L9<=7,"High","Critical"))) -> Low
A10: =DATE(2026,1,1)+INT((ROW()-2)/70) -> 46023 | B10: Gaming - Electronic | C10: EGM-SL-009 | D10: NORTH_ZONE | E10: SLOT_PROGRESSIVE | F10: 1.26 | G10: =ABS(Table2[[#This Row],[Raw_revenu_per_Hr]]) -> 95 | H10: 95 | I10: =ABS(Table2[[#This Row],[Raw_maintenance_Cost_MTBF]]) -> 120 | J10: 120 | K10: 0.91 | L10: =MAX(1,MIN(10,ROUND(10-(K10*10),0))) -> 1 | M10: Monitor | N10: Samurai 888 | O10: Konami | P10: =_xlfn.XLOOKUP(C10, Financial_Variance!B:B, Financial_Variance!H:H, 0) -> 100 | Q10: =P25-I14 -> -35 | R10: =IF(L10<=2,"Low",IF(L10<=4,"Medium",IF(L10<=7,"High","Critical"))) -> Low
A11: =DATE(2026,1,1)+INT((ROW()-2)/70) -> 46023 | B11: Gaming - Electronic | C11: EGM-SL-010 | D11: NORTH_ZONE | E11: SLOT_PROGRESSIVE | F11: 1.26 | G11: =ABS(Table2[[#This Row],[Raw_revenu_per_Hr]]) -> 95 | H11: 95 | I11: =ABS(Table2[[#This Row],[Raw_maintenance_Cost_MTBF]]) -> 120 | J11: 120 | K11: 0.91 | L11: =MAX(1,MIN(10,ROUND(10-(K11*10),0))) -> 1 | M11: Monitor | N11: Kraken Unleashed | O11: IGT | P11: =_xlfn.XLOOKUP(C11, Financial_Variance!B:B, Financial_Variance!H:H, 0) -> 100 | Q11: =P26-I15 -> -35 | R11: =IF(L11<=2,"Low",IF(L11<=4,"Medium",IF(L11<=7,"High","Critical"))) -> Low
A12: =DATE(2026,1,1)+INT((ROW()-2)/70) -> 46023 | B12: Gaming - Electronic | C12: EGM-SL-011 | D12: SOUTH_ZONE | E12: SLOT_PROGRESSIVE | F12: 1.25 | G12: =ABS(Table2[[#This Row],[Raw_revenu_per_Hr]]) -> 88 | H12: 88 | I12: =ABS(Table2[[#This Row],[Raw_maintenance_Cost_MTBF]]) -> 110 | J12: 110 | K12: 0.85 | L12: =MAX(1,MIN(10,ROUND(10-(K12*10),0))) -> 2 | M12: Monitor | N12: Huff N More Puff | O12: Aristocrat | P12: =_xlfn.XLOOKUP(C12, Financial_Variance!B:B, Financial_Variance!H:H, 0) -> 100 | Q12: =P27-I16 -> -35 | R12: =IF(L12<=2,"Low",IF(L12<=4,"Medium",IF(L12<=7,"High","Critical"))) -> Low
A13: =DATE(2026,1,1)+INT((ROW()-2)/70) -> 46023 | B13: Gaming - Electronic | C13: EGM-SL-012 | D13: SOUTH_ZONE | E13: SLOT_PROGRESSIVE | F13: 1.25 | G13: =ABS(Table2[[#This Row],[Raw_revenu_per_Hr]]) -> 88 | H13: 88 | I13: =ABS(Table2[[#This Row],[Raw_maintenance_Cost_MTBF]]) -> 110 | J13: 110 | K13: 0.85 | L13: =MAX(1,MIN(10,ROUND(10-(K13*10),0))) -> 2 | M13: Monitor | N13: Dancing Drums Explosion | O13: SG | P13: =_xlfn.XLOOKUP(C13, Financial_Variance!B:B, Financial_Variance!H:H, 0) -> 100 | Q13: =P28-I17 -> -35 | R13: =IF(L13<=2,"Low",IF(L13<=4,"Medium",IF(L13<=7,"High","Critical"))) -> Low
... A1249: =DATE(2026,1,1)+INT((ROW()-2)/70) -> 46040 | B1249: Gaming - Bingo | C1249: EGM-SL-459 | D1249: WEST_ZONE | E1249: BREAK_OPEN | F1249: 5.03 | G1249: =ABS(Table2[[#This Row],[Raw_revenu_per_Hr]]) -> 53.04 | H1249: 53.04 | I1249: =ABS(Table2[[#This Row],[Raw_maintenance_Cost_MTBF]]) -> 96.29 | J1249: 96.29 | K1249: 0.66 | L1249: =MAX(1,MIN(10,ROUND(10-(K1249*10),0))) -> 3 | M1249: Optimize | N1249: Coin Combo Mouse | O1249: Aristocrat | P1249: =_xlfn.XLOOKUP(C1249, Financial_Variance!B:B, Financial_Variance!H:H, 0) -> 0 | Q1249: =P1264-I1253 -> 0 | R1249: =IF(L1249<=2,"Low",IF(L1249<=4,"Medium",IF(L1249<=7,"High","Critical"))) -> Medium

Sheet Financial_Variance
A1: Date | B1: Asset_ID | C1: Game_Name | D1: Unit_Cost | E1: Department | F1: Location | G1: Manifactor | H1: Maintenance_Standard
A2: =DATE(2026,1,1)+INT((ROW()-2)/70) -> 46023 | B2: EGM-SL-001 | C2: Wheel of Fortune | D2: 1.26 | E2: Gaming - Electronic | F2: NORTH_ZONE | G2: IGT | H2: 100
A3: =DATE(2026,1,1)+INT((ROW()-2)/70) -> 46023 | B3: EGM-SL-002 | C3: Cash Eruption | D3: 1.26 | E3: Gaming - Electronic | F3: NORTH_ZONE | G3: IGT | H3: 100
A4: =DATE(2026,1,1)+INT((ROW()-2)/70) -> 46023 | B4: EGM-SL-003 | C4: Dancing Drums | D4: 1.26 | E4: Gaming - Electronic | F4: NORTH_ZONE | G4: SG | H4: 100
A5: =DATE(2026,1,1)+INT((ROW()-2)/70) -> 46023 | B5: EGM-SL-004 | C5: Coin Combo Mouse | D5: 1.26 | E5: Gaming - Electronic | F5: NORTH_ZONE | G5: AGS | H5: 100
A6: =DATE(2026,1,1)+INT((ROW()-2)/70) -> 46023 | B6: EGM-SL-005 | C6: Coin Combo Cow | D6: 1.26 | E6: Gaming - Electronic | F6: NORTH_ZONE | G6: AGS | H6: 100
A7: =DATE(2026,1,1)+INT((ROW()-2)/70) -> 46023 | B7: EGM-SL-006 | C7: Ultra Hot | D7: 1.26 | E7: Gaming - Electronic | F7: NORTH_ZONE | G7: IGT | H7: 100
A8: =DATE(2026,1,1)+INT((ROW()-2)/70) -> 46023 | B8: EGM-SL-007 | C8: Drop Lock | D8: 1.26 | E8: Gaming - Electronic | F8: NORTH_ZONE | G8: Bally | H8: 100
A9: =DATE(2026,1,1)+INT((ROW()-2)/70) -> 46023 | B9: EGM-SL-008 | C9: Hot Hit | D9: 1.26 | E9: Gaming - Electronic | F9: NORTH_ZONE | G9: Bally | H9: 100
A10: =DATE(2026,1,1)+INT((ROW()-2)/70) -> 46023 | B10: EGM-SL-009 | C10: Samurai 888 | D10: 1.26 | E10: Gaming - Electronic | F10: NORTH_ZONE | G10: Konami | H10: 100
A11: =DATE(2026,1,1)+INT((ROW()-2)/70) -> 46023 | B11: EGM-SL-010 | C11: Kraken Unleashed | D11: 1.26 | E11: Gaming - Electronic | F11: NORTH_ZONE | G11: IGT | H11: 100
A12: =DATE(2026,1,1)+INT((ROW()-2)/70) -> 46023 | B12: EGM-SL-011 | C12: Huff N More Puff | D12: 1.25 | E12: Gaming - Electronic | F12: SOUTH_ZONE | G12: Aristocrat | H12: 100
A13: =DATE(2026,1,1)+INT((ROW()-2)/70) -> 46023 | B13: EGM-SL-012 | C13: Dancing Drums Explosion | D13: 1.25 | E13: Gaming - Electronic | F13: SOUTH_ZONE | G13: SG | H13: 100
... A70: =DATE(2026,1,1)+INT((ROW()-2)/70) -> 46023 | B70: GSS-KI-003 | C70: Security System | D70: 0 | E70: Guest & Security | F70: CENTRAL_HUB | G70: In-House | H70: 25

Sheet Competitive_Intel
